my_package/__init__.py
my_package/tryb.py
bakul-0.1.0.dist-info/METADATA
bakul-0.1.0.dist-info/WHEEL
bakul-0.1.0.dist-info/top_level.txt
bakul-0.1.0.dist-info/RECORD
