Metadata-Version: 2.4
Name: bakul
Version: 0.1.0
Summary: A sample pip-installable Python package
Author-email: Your Name <your.email@example.com>
License: MIT
Project-URL: Homepage, https://github.com/yourusername/my-package-name
Requires-Python: >=3.6
